madsci/workcell_manager/__init__.py
madsci/workcell_manager/condition_checks.py
madsci/workcell_manager/schedulers/__init__.py
madsci/workcell_manager/schedulers/default_scheduler.py
madsci/workcell_manager/schedulers/scheduler.py
madsci/workcell_manager/schema.json
madsci/workcell_manager/state_handler.py
madsci/workcell_manager/workcell_actions.py
madsci/workcell_manager/workcell_engine.py
madsci/workcell_manager/workcell_server.py
madsci/workcell_manager/workcell_utils.py
madsci/workcell_manager/workflow_utils.py
madsci_workcell_manager-0.6.1.dist-info/METADATA
madsci_workcell_manager-0.6.1.dist-info/WHEEL
madsci_workcell_manager-0.6.1.dist-info/entry_points.txt
madsci_workcell_manager-0.6.1.dist-info/RECORD
